hindiwsd/CRF.py
hindiwsd/Hindi_WSD_Dataset - Sheet1.tsv
hindiwsd/__init__.py
hindiwsd/callbacks.py
hindiwsd/convert_encoding.py
hindiwsd/convert_ssf_conll.py
hindiwsd/crf.chunk.utf.model
hindiwsd/crf.ner.utf.model
hindiwsd/crf.pos.utf.model
hindiwsd/crf_chunk_features.py
hindiwsd/crf_pos_features.py
hindiwsd/data_reader.py
hindiwsd/evaluate.py
hindiwsd/generate_features.py
hindiwsd/hi.pkl
hindiwsd/hindi_wsd.py
hindiwsd/hipos.py
hindiwsd/layers.py
hindiwsd/lesks.py
hindiwsd/models.py
hindiwsd/out.txt
hindiwsd/pipeline.py
hindiwsd/preprocessing.py
hindiwsd/spacy_data_reader.py
hindiwsd/spacy_tagger.py
hindiwsd/spacy_tagger_test.py
hindiwsd/tagger.py
hindiwsd/test.txt
hindiwsd/trainer.py
hindiwsd/utils.py
hindiwsd/wrapper.py
hindiwsd/writer.py
hindiwsd/wsd.py
hindiwsd-1.1.2.dist-info/LICENSE
hindiwsd-1.1.2.dist-info/METADATA
hindiwsd-1.1.2.dist-info/WHEEL
hindiwsd-1.1.2.dist-info/top_level.txt
hindiwsd-1.1.2.dist-info/RECORD
